{
  "id": "078261fb-7d9e-f9ce-8760-1ba76060b04d",
  "name": "bluemix-node-starter",
  "values": [
    {
      "key": "URL",
      "value": "https://ecampbell565-bluemix-node-starter.mybluemix.net",
      "type": "text",
      "enabled": true
    },
    {
      "key": "PORT",
      "value": "62742",
      "type": "text",
      "enabled": true
    }
  ],
  "timestamp": 1482472506178,
  "_postman_variable_scope": "environment",
  "_postman_exported_at": "2016-12-23T05:55:07.282Z",
  "_postman_exported_using": "Postman/4.9.2"
}
